nodeconductor_saml2/__init__.py
nodeconductor_saml2/admin.py
nodeconductor_saml2/apps.py
nodeconductor_saml2/extension.py
nodeconductor_saml2/filters.py
nodeconductor_saml2/handlers.py
nodeconductor_saml2/log.py
nodeconductor_saml2/models.py
nodeconductor_saml2/serializers.py
nodeconductor_saml2/tasks.py
nodeconductor_saml2/urls.py
nodeconductor_saml2/utils.py
nodeconductor_saml2/views.py
nodeconductor_saml2/management/__init__.py
nodeconductor_saml2/management/commands/__init__.py
nodeconductor_saml2/management/commands/sync_saml2_providers.py
nodeconductor_saml2/migrations/0001_initial.py
nodeconductor_saml2/migrations/0002_identityprovider_metadata.py
nodeconductor_saml2/migrations/__init__.py
nodeconductor_saml2-0.7.3.dist-info/DESCRIPTION.rst
nodeconductor_saml2-0.7.3.dist-info/METADATA
nodeconductor_saml2-0.7.3.dist-info/RECORD
nodeconductor_saml2-0.7.3.dist-info/WHEEL
nodeconductor_saml2-0.7.3.dist-info/entry_points.txt
nodeconductor_saml2-0.7.3.dist-info/metadata.json
nodeconductor_saml2-0.7.3.dist-info/top_level.txt
