Metadata-Version: 2.0
Name: nodeconductor-saml2
Version: 0.7.3
Summary: Waldur plugin bringing SAML2-based authentication support.
Home-page: http://waldur.com
Author: OpenNode Team
Author-email: info@opennodecloud.com
License: MIT
Platform: UNKNOWN
Classifier: Framework :: Django
Classifier: Intended Audience :: Developers
Classifier: Intended Audience :: System Administrators
Classifier: Operating System :: OS Independent
Classifier: License :: OSI Approved :: MIT License
Requires-Dist: djangosaml2 (==0.16.0)
Requires-Dist: nodeconductor (>=0.133.0)
Provides-Extra: dev
Requires-Dist: Sphinx (==1.2.2); extra == 'dev'
